apmtools/__init__.py
apmtools/classes.py
apmtools/data_processing.py
apmtools/functions.py
apmtools-0.1.6.dist-info/METADATA
apmtools-0.1.6.dist-info/WHEEL
apmtools-0.1.6.dist-info/licenses/LICENSE
apmtools-0.1.6.dist-info/RECORD
