Metadata-Version: 2.4
Name: apmtools
Version: 0.1.6
Summary: A collection of tools for processing air pollution monitoring data
Project-URL: Homepage, https://github.com/federlorenz/apmtools
Author-email: Federico Lorenzetti <lorenzetti.federico@gmail.com>
License-File: LICENSE
Classifier: License :: OSI Approved :: MIT License
Classifier: Operating System :: OS Independent
Classifier: Programming Language :: Python :: 3
Requires-Python: >=3.8
